unix_at.py
unix_at-1.2.1.dist-info/licenses/LICENSE.txt
unix_at-1.2.1.dist-info/METADATA
unix_at-1.2.1.dist-info/WHEEL
unix_at-1.2.1.dist-info/top_level.txt
unix_at-1.2.1.dist-info/RECORD
